tasadofi/__init__.py
tasadofi/random_number.py
tests/__init__.py
tasadofi-1.0.1.dist-info/LICENSE
tasadofi-1.0.1.dist-info/METADATA
tasadofi-1.0.1.dist-info/WHEEL
tasadofi-1.0.1.dist-info/top_level.txt
tasadofi-1.0.1.dist-info/RECORD
