Metadata-Version: 2.1
Name: tasadofi
Version: 1.0.1
Summary: Python random numbers
Home-page: https://github.com/Raverss/Python-Random-Types
Author: Vojtech Molek
License: UNKNOWN
Platform: UNKNOWN
Classifier: Programming Language :: Python :: 3
Classifier: License :: OSI Approved :: MIT License
Classifier: Operating System :: OS Independent
Requires-Python: >=3.6
License-File: LICENSE
